CHANGES.txt
INSTALL.txt
LICENSE.txt
MANIFEST.in
README.txt
setup.py
Creoleparser.egg-info/PKG-INFO
Creoleparser.egg-info/SOURCES.txt
Creoleparser.egg-info/dependency_links.txt
Creoleparser.egg-info/requires.txt
Creoleparser.egg-info/top_level.txt
creoleparser/__init__.py
creoleparser/core.py
creoleparser/dialects.py
creoleparser/elements.py
creoleparser/test_arg_parser.py
creoleparser/test_cheat_sheet_plus.py
creoleparser/tests.py