Metadata-Version: 1.1
Name: Creoleparser
Version: 0.7.5
Summary: Parser for the Creole common wiki markup language
Home-page: http://code.google.com/p/creoleparser/
Author: Stephen Day
Author-email: UNKNOWN
License: MIT
Download-URL: http://pypi.python.org/pypi/Creoleparser
Platform: UNKNOWN
Classifier: Development Status :: 4 - Beta
Classifier: Environment :: Web Environment
Classifier: Intended Audience :: Developers
Classifier: License :: OSI Approved :: MIT License
Classifier: Operating System :: OS Independent
Classifier: Programming Language :: Python
Classifier: Programming Language :: Python :: 2
Classifier: Programming Language :: Python :: 3
Classifier: Topic :: Internet :: WWW/HTTP :: Dynamic Content
Classifier: Topic :: Software Development :: Libraries :: Python Modules
Classifier: Topic :: Text Processing :: Markup
Classifier: Topic :: Text Processing :: Markup :: HTML
Classifier: Topic :: Text Processing :: Markup :: XML
